pifetcher/__init__.py
pifetcher/config.json
pifetcher/core/__init__.py
pifetcher/core/config.py
pifetcher/core/fetch_worker.py
pifetcher/core/fetcher_factory.py
pifetcher/core/logger.py
pifetcher/data_fetchers/__init__.py
pifetcher/data_fetchers/base_data_fetcher.py
pifetcher/data_fetchers/fetcher_factory.py
pifetcher/data_fetchers/http_request_fetcher.py
pifetcher/data_fetchers/pyppeteer_fetcher.py
pifetcher/drivers/chromedriver-linux-76
pifetcher/drivers/chromedriver-linux-80
pifetcher/drivers/chromedriver-mac-76
pifetcher/drivers/chromedriver-win-76.exe
pifetcher/drivers/geckodriver.exe
pifetcher/utilities/__init__.py
pifetcher/utilities/config_utilities.py
pifetcher/utilities/data_utils.py
pifetcher/utilities/sys_utils.py
pifetcher/work_queue/__init__.py
pifetcher/work_queue/base_work_queue.py
pifetcher/work_queue/local_work_queue.py
pifetcher/work_queue/sqs_work_queue.py
pifetcher/work_queue/work_queue_factory.py
pifetcher-0.0.3.7.dist-info/DESCRIPTION.rst
pifetcher-0.0.3.7.dist-info/METADATA
pifetcher-0.0.3.7.dist-info/RECORD
pifetcher-0.0.3.7.dist-info/WHEEL
pifetcher-0.0.3.7.dist-info/metadata.json
pifetcher-0.0.3.7.dist-info/top_level.txt
