Metadata-Version: 2.0
Name: pifetcher
Version: 0.0.3.7
Summary: A scalable headless data fetching library written with python and message queue service to enable quickly and easily prasing web data in a distributive way.
Home-page: https://github.com/gavinz0228/pifetcher
Author: Gavin Zhang
Author-email: gavinz0228@gmail.com
License: UNKNOWN
Platform: UNKNOWN
Classifier: Programming Language :: Python :: 3
Classifier: License :: OSI Approved :: MIT License
Classifier: Operating System :: MacOS :: MacOS X
Classifier: Operating System :: Microsoft :: Windows
Classifier: Operating System :: POSIX
Requires-Dist: bs4
Requires-Dist: boto3
Requires-Dist: requests
Requires-Dist: pyppeteer
